caveclient/__init__.py
caveclient/__main__.py
caveclient/annotationengine.py
caveclient/auth.py
caveclient/base.py
caveclient/chunkedgraph.py
caveclient/datastack_lookup.py
caveclient/emannotationschemas.py
caveclient/endpoints.py
caveclient/format_utils.py
caveclient/frameworkclient.py
caveclient/infoservice.py
caveclient/jsonservice.py
caveclient/l2cache.py
caveclient/materializationengine.py
caveclient/mytimer.py
caveclient/session_config.py
caveclient/skeletonservice.py
caveclient/tools/__init__.py
caveclient/tools/caching.py
caveclient/tools/stage.py
caveclient/tools/table_manager.py
caveclient/tools/testing.py
caveclient-7.11.1.dist-info/METADATA
caveclient-7.11.1.dist-info/WHEEL
caveclient-7.11.1.dist-info/entry_points.txt
caveclient-7.11.1.dist-info/licenses/LICENSE
caveclient-7.11.1.dist-info/RECORD
