Metadata-Version: 2.4
Name: caveclient
Version: 7.11.1
Summary: A client for interacting with the Connectome Annotation Versioning Engine
Project-URL: Documentation, https://caveconnectome.github.io/CAVEclient/
Project-URL: Homepage, https://caveconnectome.github.io/CAVEclient/
Project-URL: Issues, https://github.com/CAVEconnectome/CAVEclient/issues
Project-URL: Repository, https://github.com/CAVEconnectome/CAVEclient/
Author: CAVE Developers
Maintainer: CAVE Developers
License-Expression: MIT
License-File: LICENSE
Requires-Python: >=3.9
Requires-Dist: attrs>=21.3.0
Requires-Dist: cachetools>=4.2.1
Requires-Dist: ipython>6
Requires-Dist: jsonschema
Requires-Dist: networkx
Requires-Dist: numpy>1.19.3
Requires-Dist: packaging>=24.1
Requires-Dist: pandas<3.0.0
Requires-Dist: pyarrow>=3
Requires-Dist: requests
Requires-Dist: urllib3
Provides-Extra: cv
Requires-Dist: cloud-volume; extra == 'cv'
